extendspace/__init__.py
extendspace/extend.py
extendspace/extendspace.py
serving/__init__.py
serving/uwsgi_main.py
extendspace-1.1.1.dist-info/METADATA
extendspace-1.1.1.dist-info/WHEEL
extendspace-1.1.1.dist-info/top_level.txt
extendspace-1.1.1.dist-info/RECORD
